{
    "children": [
        {
            "children": [
                {
                    "color": "#3c7263",
                    "name": "response execution",
                    "nid": "trm_557b4a7315f1b"
                },
                {
                    "color": "#3c7263",
                    "name": "response selection",
                    "nid": "trm_4a3fd79d0af71"
                },
                {
                    "color": "#3c7263",
                    "name": "visual form recognition",
                    "nid": "trm_557b4b3a6a34d"
                },
                {
                    "color": "#3c7263",
                    "name": "auditory tone detection",
                    "nid": "trm_557b474e2b578"
                },
                {
                    "color": "#3c7263",
                    "name": "oddball detection",
                    "nid": "trm_557b491318742"
                },
                {
                    "color": "#3c7263",
                    "name": "selective control",
                    "nid": "trm_557b4aa070c10"
                },
                {
                    "color": "#3c7263",
                    "name": "error detection",
                    "nid": "trm_4a3fd79d0a20c"
                },
                {
                    "color": "#3c7263",
                    "name": "proactive control",
                    "nid": "trm_557b49851e991"
                },
                {
                    "color": "#3c7263",
                    "name": "response inhibition",
                    "nid": "trm_4a3fd79d0af66"
                }
            ],
            "color": "#d89013",
            "name": "go-critical",
            "nid": "cnt_55399ad50b4f4"
        },
        {
            "children": [
                {
                    "color": "#3c7263",
                    "name": "response execution",
                    "nid": "trm_557b4a7315f1b"
                },
                {
                    "color": "#3c7263",
                    "name": "response selection",
                    "nid": "trm_4a3fd79d0af71"
                },
                {
                    "color": "#3c7263",
                    "name": "visual form recognition",
                    "nid": "trm_557b4b3a6a34d"
                },
                {
                    "color": "#3c7263",
                    "name": "auditory tone detection",
                    "nid": "trm_557b474e2b578"
                },
                {
                    "color": "#3c7263",
                    "name": "oddball detection",
                    "nid": "trm_557b491318742"
                },
                {
                    "color": "#3c7263",
                    "name": "selective control",
                    "nid": "trm_557b4aa070c10"
                },
                {
                    "color": "#3c7263",
                    "name": "error detection",
                    "nid": "trm_4a3fd79d0a20c"
                },
                {
                    "color": "#3c7263",
                    "name": "proactive control",
                    "nid": "trm_557b49851e991"
                },
                {
                    "color": "#3c7263",
                    "name": "response inhibition",
                    "nid": "trm_4a3fd79d0af66"
                }
            ],
            "color": "#d89013",
            "name": "stop-critical trial",
            "nid": "cnt_4cacf44631b29"
        },
        {
            "children": [
                {
                    "color": "#3c7263",
                    "name": "response execution",
                    "nid": "trm_557b4a7315f1b"
                },
                {
                    "color": "#3c7263",
                    "name": "response selection",
                    "nid": "trm_4a3fd79d0af71"
                },
                {
                    "color": "#3c7263",
                    "name": "visual form recognition",
                    "nid": "trm_557b4b3a6a34d"
                },
                {
                    "color": "#3c7263",
                    "name": "auditory tone detection",
                    "nid": "trm_557b474e2b578"
                },
                {
                    "color": "#3c7263",
                    "name": "oddball detection",
                    "nid": "trm_557b491318742"
                },
                {
                    "color": "#3c7263",
                    "name": "selective control",
                    "nid": "trm_557b4aa070c10"
                },
                {
                    "color": "#3c7263",
                    "name": "error detection",
                    "nid": "trm_4a3fd79d0a20c"
                },
                {
                    "color": "#3c7263",
                    "name": "proactive control",
                    "nid": "trm_557b49851e991"
                },
                {
                    "color": "#3c7263",
                    "name": "response inhibition",
                    "nid": "trm_4a3fd79d0af66"
                }
            ],
            "color": "#d89013",
            "name": "stop-noncritical trial",
            "nid": "cnt_4cacf4680bbcd"
        },
        {
            "children": [
                {
                    "color": "#3c7263",
                    "name": "response execution",
                    "nid": "trm_557b4a7315f1b"
                },
                {
                    "color": "#3c7263",
                    "name": "response selection",
                    "nid": "trm_4a3fd79d0af71"
                },
                {
                    "color": "#3c7263",
                    "name": "visual form recognition",
                    "nid": "trm_557b4b3a6a34d"
                },
                {
                    "color": "#3c7263",
                    "name": "auditory tone detection",
                    "nid": "trm_557b474e2b578"
                },
                {
                    "color": "#3c7263",
                    "name": "oddball detection",
                    "nid": "trm_557b491318742"
                },
                {
                    "color": "#3c7263",
                    "name": "selective control",
                    "nid": "trm_557b4aa070c10"
                },
                {
                    "color": "#3c7263",
                    "name": "error detection",
                    "nid": "trm_4a3fd79d0a20c"
                },
                {
                    "color": "#3c7263",
                    "name": "proactive control",
                    "nid": "trm_557b49851e991"
                },
                {
                    "color": "#3c7263",
                    "name": "response inhibition",
                    "nid": "trm_4a3fd79d0af66"
                }
            ],
            "color": "#d89013",
            "name": "successful stop minus go",
            "nid": "cnt_4ebca1f15eb7d"
        },
        {
            "children": [
                {
                    "color": "#3c7263",
                    "name": "response execution",
                    "nid": "trm_557b4a7315f1b"
                },
                {
                    "color": "#3c7263",
                    "name": "response selection",
                    "nid": "trm_4a3fd79d0af71"
                },
                {
                    "color": "#3c7263",
                    "name": "visual form recognition",
                    "nid": "trm_557b4b3a6a34d"
                },
                {
                    "color": "#3c7263",
                    "name": "auditory tone detection",
                    "nid": "trm_557b474e2b578"
                },
                {
                    "color": "#3c7263",
                    "name": "oddball detection",
                    "nid": "trm_557b491318742"
                },
                {
                    "color": "#3c7263",
                    "name": "selective control",
                    "nid": "trm_557b4aa070c10"
                },
                {
                    "color": "#3c7263",
                    "name": "error detection",
                    "nid": "trm_4a3fd79d0a20c"
                },
                {
                    "color": "#3c7263",
                    "name": "proactive control",
                    "nid": "trm_557b49851e991"
                },
                {
                    "color": "#3c7263",
                    "name": "response inhibition",
                    "nid": "trm_4a3fd79d0af66"
                }
            ],
            "color": "#d89013",
            "name": "failed stop-critical ",
            "nid": "cnt_4ebca202935c6"
        },
        {
            "children": [
                {
                    "color": "#3c7263",
                    "name": "response execution",
                    "nid": "trm_557b4a7315f1b"
                },
                {
                    "color": "#3c7263",
                    "name": "response selection",
                    "nid": "trm_4a3fd79d0af71"
                },
                {
                    "color": "#3c7263",
                    "name": "visual form recognition",
                    "nid": "trm_557b4b3a6a34d"
                },
                {
                    "color": "#3c7263",
                    "name": "auditory tone detection",
                    "nid": "trm_557b474e2b578"
                },
                {
                    "color": "#3c7263",
                    "name": "oddball detection",
                    "nid": "trm_557b491318742"
                },
                {
                    "color": "#3c7263",
                    "name": "selective control",
                    "nid": "trm_557b4aa070c10"
                },
                {
                    "color": "#3c7263",
                    "name": "error detection",
                    "nid": "trm_4a3fd79d0a20c"
                },
                {
                    "color": "#3c7263",
                    "name": "proactive control",
                    "nid": "trm_557b49851e991"
                },
                {
                    "color": "#3c7263",
                    "name": "response inhibition",
                    "nid": "trm_4a3fd79d0af66"
                }
            ],
            "color": "#d89013",
            "name": "failed stop-noncritical ",
            "nid": "cnt_4ebca22149619"
        },
        {
            "children": [
                {
                    "color": "#3c7263",
                    "name": "response execution",
                    "nid": "trm_557b4a7315f1b"
                },
                {
                    "color": "#3c7263",
                    "name": "response selection",
                    "nid": "trm_4a3fd79d0af71"
                },
                {
                    "color": "#3c7263",
                    "name": "visual form recognition",
                    "nid": "trm_557b4b3a6a34d"
                },
                {
                    "color": "#3c7263",
                    "name": "auditory tone detection",
                    "nid": "trm_557b474e2b578"
                },
                {
                    "color": "#3c7263",
                    "name": "oddball detection",
                    "nid": "trm_557b491318742"
                },
                {
                    "color": "#3c7263",
                    "name": "selective control",
                    "nid": "trm_557b4aa070c10"
                },
                {
                    "color": "#3c7263",
                    "name": "error detection",
                    "nid": "trm_4a3fd79d0a20c"
                },
                {
                    "color": "#3c7263",
                    "name": "proactive control",
                    "nid": "trm_557b49851e991"
                },
                {
                    "color": "#3c7263",
                    "name": "response inhibition",
                    "nid": "trm_4a3fd79d0af66"
                }
            ],
            "color": "#d89013",
            "name": "junk ",
            "nid": "cnt_4ebca2351bb79"
        },
        {
            "children": [
                {
                    "color": "#3c7263",
                    "name": "response execution",
                    "nid": "trm_557b4a7315f1b"
                },
                {
                    "color": "#3c7263",
                    "name": "response selection",
                    "nid": "trm_4a3fd79d0af71"
                },
                {
                    "color": "#3c7263",
                    "name": "visual form recognition",
                    "nid": "trm_557b4b3a6a34d"
                },
                {
                    "color": "#3c7263",
                    "name": "auditory tone detection",
                    "nid": "trm_557b474e2b578"
                },
                {
                    "color": "#3c7263",
                    "name": "oddball detection",
                    "nid": "trm_557b491318742"
                },
                {
                    "color": "#3c7263",
                    "name": "selective control",
                    "nid": "trm_557b4aa070c10"
                },
                {
                    "color": "#3c7263",
                    "name": "error detection",
                    "nid": "trm_4a3fd79d0a20c"
                },
                {
                    "color": "#3c7263",
                    "name": "proactive control",
                    "nid": "trm_557b49851e991"
                },
                {
                    "color": "#3c7263",
                    "name": "response inhibition",
                    "nid": "trm_4a3fd79d0af66"
                }
            ],
            "color": "#d89013",
            "name": "go-critical minus go-noncritical",
            "nid": "cnt_553999f2c69ef"
        },
        {
            "children": [
                {
                    "color": "#3c7263",
                    "name": "response execution",
                    "nid": "trm_557b4a7315f1b"
                },
                {
                    "color": "#3c7263",
                    "name": "response selection",
                    "nid": "trm_4a3fd79d0af71"
                },
                {
                    "color": "#3c7263",
                    "name": "visual form recognition",
                    "nid": "trm_557b4b3a6a34d"
                },
                {
                    "color": "#3c7263",
                    "name": "auditory tone detection",
                    "nid": "trm_557b474e2b578"
                },
                {
                    "color": "#3c7263",
                    "name": "oddball detection",
                    "nid": "trm_557b491318742"
                },
                {
                    "color": "#3c7263",
                    "name": "selective control",
                    "nid": "trm_557b4aa070c10"
                },
                {
                    "color": "#3c7263",
                    "name": "error detection",
                    "nid": "trm_4a3fd79d0a20c"
                },
                {
                    "color": "#3c7263",
                    "name": "proactive control",
                    "nid": "trm_557b49851e991"
                },
                {
                    "color": "#3c7263",
                    "name": "response inhibition",
                    "nid": "trm_4a3fd79d0af66"
                }
            ],
            "color": "#d89013",
            "name": "unsuccessful stop minus successful stop",
            "nid": "cnt_55399a008d960"
        },
        {
            "children": [
                {
                    "color": "#3c7263",
                    "name": "response execution",
                    "nid": "trm_557b4a7315f1b"
                },
                {
                    "color": "#3c7263",
                    "name": "response selection",
                    "nid": "trm_4a3fd79d0af71"
                },
                {
                    "color": "#3c7263",
                    "name": "visual form recognition",
                    "nid": "trm_557b4b3a6a34d"
                },
                {
                    "color": "#3c7263",
                    "name": "auditory tone detection",
                    "nid": "trm_557b474e2b578"
                },
                {
                    "color": "#3c7263",
                    "name": "oddball detection",
                    "nid": "trm_557b491318742"
                },
                {
                    "color": "#3c7263",
                    "name": "selective control",
                    "nid": "trm_557b4aa070c10"
                },
                {
                    "color": "#3c7263",
                    "name": "error detection",
                    "nid": "trm_4a3fd79d0a20c"
                },
                {
                    "color": "#3c7263",
                    "name": "proactive control",
                    "nid": "trm_557b49851e991"
                },
                {
                    "color": "#3c7263",
                    "name": "response inhibition",
                    "nid": "trm_4a3fd79d0af66"
                }
            ],
            "color": "#d89013",
            "name": "go-noncritical",
            "nid": "cnt_55399a202b4ff"
        },
        {
            "children": [
                {
                    "color": "#3c7263",
                    "name": "response execution",
                    "nid": "trm_557b4a7315f1b"
                },
                {
                    "color": "#3c7263",
                    "name": "response selection",
                    "nid": "trm_4a3fd79d0af71"
                },
                {
                    "color": "#3c7263",
                    "name": "visual form recognition",
                    "nid": "trm_557b4b3a6a34d"
                },
                {
                    "color": "#3c7263",
                    "name": "auditory tone detection",
                    "nid": "trm_557b474e2b578"
                },
                {
                    "color": "#3c7263",
                    "name": "oddball detection",
                    "nid": "trm_557b491318742"
                },
                {
                    "color": "#3c7263",
                    "name": "selective control",
                    "nid": "trm_557b4aa070c10"
                },
                {
                    "color": "#3c7263",
                    "name": "error detection",
                    "nid": "trm_4a3fd79d0a20c"
                },
                {
                    "color": "#3c7263",
                    "name": "proactive control",
                    "nid": "trm_557b49851e991"
                },
                {
                    "color": "#3c7263",
                    "name": "response inhibition",
                    "nid": "trm_4a3fd79d0af66"
                }
            ],
            "color": "#d89013",
            "name": "all",
            "nid": "cnt_55399c9a3ae82"
        },
        {
            "children": [
                {
                    "color": "#3c7263",
                    "name": "response execution",
                    "nid": "trm_557b4a7315f1b"
                },
                {
                    "color": "#3c7263",
                    "name": "response selection",
                    "nid": "trm_4a3fd79d0af71"
                },
                {
                    "color": "#3c7263",
                    "name": "visual form recognition",
                    "nid": "trm_557b4b3a6a34d"
                },
                {
                    "color": "#3c7263",
                    "name": "auditory tone detection",
                    "nid": "trm_557b474e2b578"
                },
                {
                    "color": "#3c7263",
                    "name": "oddball detection",
                    "nid": "trm_557b491318742"
                },
                {
                    "color": "#3c7263",
                    "name": "selective control",
                    "nid": "trm_557b4aa070c10"
                },
                {
                    "color": "#3c7263",
                    "name": "error detection",
                    "nid": "trm_4a3fd79d0a20c"
                },
                {
                    "color": "#3c7263",
                    "name": "proactive control",
                    "nid": "trm_557b49851e991"
                },
                {
                    "color": "#3c7263",
                    "name": "response inhibition",
                    "nid": "trm_4a3fd79d0af66"
                }
            ],
            "color": "#d89013",
            "name": "successful stop-critical",
            "nid": "cnt_55399a3f5e512"
        }
    ],
    "color": "#63506d",
    "name": "conditional stop signal task",
    "nid": "trm_4cacf3fbc503b"
}