{
    "children": [
        {
            "children": [
                {
                    "color": "#3c7263",
                    "name": "visual perception",
                    "nid": "trm_4a3fd79d0b4b5"
                },
                {
                    "color": "#3c7263",
                    "name": "emotion recognition",
                    "nid": "trm_4a3fd79d0b665"
                }
            ],
            "color": "#d89013",
            "name": "percent correct",
            "nid": "cnt_50f73673c04d8"
        }
    ],
    "color": "#63506d",
    "name": "Emotion Recognition Task",
    "nid": "trm_50f734f86b11a"
}