{
    "children": [
        {
            "children": [
                {
                    "color": "#3c7263",
                    "name": "response execution",
                    "nid": "trm_557b4a7315f1b"
                }
            ],
            "color": "#d89013",
            "name": "areas of activation during task minus baseline",
            "nid": "cnt_4e0181c976a19"
        },
        {
            "children": [
                {
                    "color": "#3c7263",
                    "name": "response execution",
                    "nid": "trm_557b4a7315f1b"
                }
            ],
            "color": "#d89013",
            "name": "response time of subject minus response time of controls",
            "nid": "cnt_4e0182336c9cc"
        }
    ],
    "color": "#63506d",
    "name": "whistling",
    "nid": "trm_4c8a8575d1e55"
}